async_oauthlib/__init__.py
async_oauthlib/oauth1_auth.py
async_oauthlib/oauth1_session.py
async_oauthlib/oauth2_auth.py
async_oauthlib/oauth2_session.py
async_oauthlib/utils.py
async_oauthlib/compliance_fixes/__init__.py
async_oauthlib/compliance_fixes/douban.py
async_oauthlib/compliance_fixes/facebook.py
async_oauthlib/compliance_fixes/fitbit.py
async_oauthlib/compliance_fixes/instagram.py
async_oauthlib/compliance_fixes/mailchimp.py
async_oauthlib/compliance_fixes/plentymarkets.py
async_oauthlib/compliance_fixes/slack.py
async_oauthlib/compliance_fixes/weibo.py
Async_OAuthlib-0.0.9.dist-info/LICENSE
Async_OAuthlib-0.0.9.dist-info/METADATA
Async_OAuthlib-0.0.9.dist-info/WHEEL
Async_OAuthlib-0.0.9.dist-info/top_level.txt
Async_OAuthlib-0.0.9.dist-info/RECORD
